ai_care/__init__.py
ai_care/_version.py
ai_care/abilities.py
ai_care/ai_care.py
ai_care/choice_execute.py
ai_care/parse_response.py
ai_care/render_prompt.py
ai_care-0.1.3.dist-info/LICENSE
ai_care-0.1.3.dist-info/METADATA
ai_care-0.1.3.dist-info/WHEEL
ai_care-0.1.3.dist-info/top_level.txt
ai_care-0.1.3.dist-info/RECORD
