Metadata-Version: 2.1
Name: ai-care
Version: 0.1.3
Summary: AI-Care endows AI with the capability to speak proactively. With simple settings, AI-Care allows your AI to proactively care for you.
Author-email: Xueao Chao <chaoxueao@gmail.com>
License: MIT License
Project-URL: Homepage, https://github.com/happyapplehorse/ai-care
Project-URL: Issues, https://github.com/happyapplehorse/ai-care/issues
Keywords: AI,Proactive AI,LLM
Classifier: Development Status :: 3 - Alpha
Classifier: Intended Audience :: Developers
Classifier: Topic :: Software Development
Classifier: Topic :: Scientific/Engineering :: Artificial Intelligence
Classifier: Topic :: Software Development :: Libraries
Classifier: Topic :: Software Development :: Libraries :: Python Modules
Classifier: Topic :: Utilities
Classifier: Programming Language :: Python :: 3
Classifier: License :: OSI Approved :: MIT License
Classifier: Operating System :: OS Independent
Requires-Python: >=3.10
License-File: LICENSE
